tfx_helper/__init__.py
tfx_helper/base.py
tfx_helper/interface.py
tfx_helper/local.py
tfx_helper/py.typed
tfx_helper/vertex_ai.py
tfx_helper/artifact_finder/__init__.py
tfx_helper/artifact_finder/interface.py
tfx_helper/artifact_finder/local.py
tfx_helper/artifact_finder/ml_metadata.py
tfx_helper/artifact_finder/vertex_ai.py
tfx_helper/components/__init__.py
tfx_helper/components/threshold_optimizer/__init__.py
tfx_helper/components/threshold_optimizer/component.py
tfx_helper/visualization/__init__.py
tfx_helper/visualization/confusion_matrix.py
tfx_helper/visualization/display_anomalies.py
tfx_helper/visualization/display_hyperparams.py
tfx_helper/visualization/display_metrics.py
tfx_helper/visualization/display_schema.py
tfx_helper/visualization/display_stats.py
tfx_helper/visualization/display_value_artifact.py
tfx_helper/visualization/threshold_optimization.py
tfx_helper/visualization/utils.py
tfx_helper-0.2.4.dist-info/LICENSE
tfx_helper-0.2.4.dist-info/METADATA
tfx_helper-0.2.4.dist-info/WHEEL
tfx_helper-0.2.4.dist-info/top_level.txt
tfx_helper-0.2.4.dist-info/RECORD
