Metadata-Version: 2.1
Name: tfx-helper
Version: 0.2.4
Summary: A helper library for TFX
Home-page: https://github.com/dlabsai/tfx-helper
Author: Tomasz Maćkowiak
Author-email: tomasz.mackowiak@dlabs.ai
Project-URL: Bug Tracker, https://github.com/dlabsai/tfx-helper/issues
Classifier: Programming Language :: Python :: 3
Classifier: License :: OSI Approved :: MIT License
Classifier: Operating System :: OS Independent
Requires-Python: >=3.7
License-File: LICENSE
Requires-Dist: tfx[kfp] (<2,>=1.6.1)
Requires-Dist: google-cloud-aiplatform
Requires-Dist: pydantic
Requires-Dist: typing-extensions
Requires-Dist: absl-py
Requires-Dist: numpy
Requires-Dist: matplotlib
